YunhuAdapter/Converter.py
YunhuAdapter/Core.py
YunhuAdapter/__init__.py
erispulse_yunhuadapter-3.5.1.dist-info/licenses/LICENSE
erispulse_yunhuadapter-3.5.1.dist-info/METADATA
erispulse_yunhuadapter-3.5.1.dist-info/WHEEL
erispulse_yunhuadapter-3.5.1.dist-info/entry_points.txt
erispulse_yunhuadapter-3.5.1.dist-info/top_level.txt
erispulse_yunhuadapter-3.5.1.dist-info/RECORD
