Metadata-Version: 2.4
Name: ErisPulse-YunhuAdapter
Version: 3.5.1
Summary: ErisPulse的云湖协议适配模块
Author-email: wsu2059 <wsu2059@qq.com>
License: MIT License
Project-URL: homepage, https://github.com/ErisPulse/ErisPulse-YunhuAdapter
Requires-Python: >=3.10
License-File: LICENSE
Requires-Dist: aiohttp
Requires-Dist: filetype
Dynamic: license-file
